themis.attack-1.0.0-py2.7-nspkg.pth
themis/attack/__about__.py
themis/attack/__init__.py
themis/attack/main.py
themis.attack-1.0.0.dist-info/DESCRIPTION.rst
themis.attack-1.0.0.dist-info/entry_points.txt
themis.attack-1.0.0.dist-info/METADATA
themis.attack-1.0.0.dist-info/metadata.json
themis.attack-1.0.0.dist-info/namespace_packages.txt
themis.attack-1.0.0.dist-info/pbr.json
themis.attack-1.0.0.dist-info/RECORD
themis.attack-1.0.0.dist-info/top_level.txt
themis.attack-1.0.0.dist-info/WHEEL
