Metadata-Version: 2.0
Name: themis.attack
Version: 1.0.0
Summary: Themis Finals attack helper library
Home-page: https://github.com/aspyatkin/themis-attack-py
Author: Alexander Pyatkin
Author-email: asp@thexyz.net
License: MIT
Platform: UNKNOWN
Requires-Dist: setuptools
Requires-Dist: enum34 (>=1.0)
Requires-Dist: requests (>=2.7)
